eVAIRpathplanning/RRT.py
eVAIRpathplanning/__init__.py
eVAIRpathplanning/spline.py
evairpathplanning-0.1.dist-info/METADATA
evairpathplanning-0.1.dist-info/WHEEL
evairpathplanning-0.1.dist-info/top_level.txt
evairpathplanning-0.1.dist-info/RECORD
