Metadata-Version: 2.4
Name: eVAIRpathplanning
Version: 0.1
Summary: eVAIR Path Planning codes
Author: Eugene H. Kim
Author-email: eugenekim00000@gmail.com
Requires-Dist: numpy>=2.1.1
Dynamic: author
Dynamic: author-email
Dynamic: requires-dist
Dynamic: summary
